anova_analysis/ANOVA_RBD.py
anova_analysis/__init__.py
anova_analysis/example.py
anova_analysis-1.0.5.dist-info/LICENSE
anova_analysis-1.0.5.dist-info/METADATA
anova_analysis-1.0.5.dist-info/WHEEL
anova_analysis-1.0.5.dist-info/top_level.txt
anova_analysis-1.0.5.dist-info/RECORD
