Metadata-Version: 2.1
Name: anova-analysis
Version: 1.0.5
Summary: A package for performing ANOVA analysis by RBD
Home-page: https://github.com/Insight-deviler/anova_analysis
Author-email: insightagri10@gmail.com
License: MIT
Keywords: line x tester,lxt,Line x Tester,Line Tester,Genetics and Plant breeding,Quantitative Genetics,ANOVA,Two-way ANOVA,RBD,analysis of variance
Classifier: Programming Language :: Python :: 3
Classifier: License :: OSI Approved :: MIT License
Classifier: Operating System :: OS Independent
Requires-Python: >=3.6
License-File: LICENSE
Requires-Dist: tabulate
Requires-Dist: pandas
Requires-Dist: scipy
Requires-Dist: numpy
